main.py
mseep_k6_mcp_server-0.1.4.dist-info/licenses/LICENSE
mseep_k6_mcp_server-0.1.4.dist-info/METADATA
mseep_k6_mcp_server-0.1.4.dist-info/WHEEL
mseep_k6_mcp_server-0.1.4.dist-info/entry_points.txt
mseep_k6_mcp_server-0.1.4.dist-info/top_level.txt
mseep_k6_mcp_server-0.1.4.dist-info/RECORD
