Metadata-Version: 2.4
Name: mseep-k6-mcp-server
Version: 0.1.4
Summary: Model context protocol server for k6 load testing
Author-email: mseep <support@skydeck.ai>
Requires-Python: >=3.12
License-File: LICENSE
Requires-Dist: mcp[cli]>=1.6.0
Dynamic: license-file
